{
  "project_info": {
    "project_number": "1046645912561",
    "firebase_url": "https://task-app-224cb.firebaseio.com",
    "project_id": "task-app-224cb",
    "storage_bucket": "task-app-224cb.appspot.com"
  },
  "client": [
    {
      "client_info": {
        "mobilesdk_app_id": "1:1046645912561:android:a6149198d1c3e6d9",
        "android_client_info": {
          "package_name": "com.example.srinivasan.taskapp"
        }
      },
      "oauth_client": [
        {
          "client_id": "1046645912561-oo82j440nvnrs8kki6p0eqens044rqd6.apps.googleusercontent.com",
          "client_type": 3
        }
      ],
      "api_key": [
        {
          "current_key": "AIzaSyAbIrZ-4cJaT8OZomsa5JPsX1MEVDLZMrQ"
        }
      ],
      "services": {
        "analytics_service": {
          "status": 1
        },
        "appinvite_service": {
          "status": 1,
          "other_platform_oauth_client": []
        },
        "ads_service": {
          "status": 2
        }
      }
    }
  ],
  "configuration_version": "1"
}